emojix.py
emojix-0.0.1.dist-info/LICENSE
emojix-0.0.1.dist-info/METADATA
emojix-0.0.1.dist-info/WHEEL
emojix-0.0.1.dist-info/top_level.txt
emojix-0.0.1.dist-info/RECORD
