Metadata-Version: 2.1
Name: emojix
Version: 0.0.1
Summary: Utility functions for emoji manipulation in Python
Classifier: Programming Language :: Python :: 3
Classifier: License :: OSI Approved :: MIT License
Classifier: Operating System :: OS Independent
Requires-Python: >=3.6
License-File: LICENSE
